cmdfixer/__init__.py
cmdfixer/main.py
cmdfixer/cli/__init__.py
cmdfixer/cli/commands.py
cmdfixer/cli/utils.py
cmdfixer/executor/__init__.py
cmdfixer/executor/executor.py
cmdfixer/llm/__init__.py
cmdfixer/llm/abstract_llm_model.py
cmdfixer/llm/gemini_preview_llm.py
cmdfixer/prompt/__init__.py
cmdfixer/prompt/abstract_prompt_builder.py
cmdfixer/prompt/cmd_fix_prompt.py
cmdfixer_gemini-0.1.9.dist-info/licenses/LICENSE
cmdfixer_gemini-0.1.9.dist-info/METADATA
cmdfixer_gemini-0.1.9.dist-info/WHEEL
cmdfixer_gemini-0.1.9.dist-info/entry_points.txt
cmdfixer_gemini-0.1.9.dist-info/top_level.txt
cmdfixer_gemini-0.1.9.dist-info/RECORD
