Metadata-Version: 2.4
Name: cmdfixer-gemini
Version: 0.1.9
Summary: Fix corrupted shell commands using AI
Author-email: Mostafa Osman <mostafa.osman.fathi@gmail.com>
License: MIT
Project-URL: homepage, https://github.com/MostafaOsmanFathi/Cmd-Fixer
Keywords: CLI,AI,command-fixer,shell
Requires-Python: >=3.10
License-File: LICENSE
Requires-Dist: click<9.0,>=8.0
Requires-Dist: google-genai<2.0.0,>=1.20.0
Requires-Dist: toml<1.0,>=0.10.0
Requires-Dist: google-auth<3.0.0,>=2.14.1
Dynamic: license-file
